LICENSE
MANIFEST.in
README.md
setup.py
vdt/__init__.py
vdt.versionplugin.debianize.egg-info/PKG-INFO
vdt.versionplugin.debianize.egg-info/SOURCES.txt
vdt.versionplugin.debianize.egg-info/dependency_links.txt
vdt.versionplugin.debianize.egg-info/entry_points.txt
vdt.versionplugin.debianize.egg-info/namespace_packages.txt
vdt.versionplugin.debianize.egg-info/requires.txt
vdt.versionplugin.debianize.egg-info/top_level.txt
vdt.versionplugin.debianize.egg-info/zip-safe
vdt/versionplugin/__init__.py
vdt/versionplugin/debianize/__init__.py
vdt/versionplugin/debianize/config.py
vdt/versionplugin/debianize/fpmeditor.py
vdt/versionplugin/debianize/package.py
vdt/versionplugin/debianize/shared.py
vdt/versionplugin/debianize/files/preremove.sh